[
  {
    "idx": 1,
    "slug": "posd-lint",
    "title": "posd-lint",
    "blurb": "static analysis tool surfacing violations of a philosophy of software design. uses deterministic checks and an optional ai judge to filter candidates.",
    "longBlurb": "",
    "writeup": "",
    "tags": [
      "PYTHON"
    ],
    "meta": "updated may 2026",
    "stack": "Python",
    "status": "active",
    "featured": false,
    "screenshot": "",
    "links": {
      "repo": "https://github.com/SirWhack/posd-lint",
      "demo": "",
      "writeup": ""
    }
  },
  {
    "idx": 2,
    "slug": "banana-gun",
    "title": "banana-gun",
    "blurb": "reproduction of the sleeper agents paper on gemma 4 e4b. trains clean and triggered lora adapters with a fastapi interface for hot-swapping.",
    "longBlurb": "",
    "writeup": "",
    "tags": [
      "PYTHON"
    ],
    "meta": "updated may 2026",
    "stack": "Python",
    "status": "active",
    "featured": false,
    "screenshot": "",
    "links": {
      "repo": "https://github.com/SirWhack/banana-gun",
      "demo": "",
      "writeup": ""
    }
  },
  {
    "idx": 3,
    "slug": "lifestrands",
    "title": "LifeStrands",
    "blurb": "ai npc system using python microservices for background memory and summary processing.",
    "longBlurb": "",
    "writeup": "",
    "tags": [
      "PYTHON"
    ],
    "meta": "updated sep 2025",
    "stack": "Python",
    "status": "active",
    "featured": false,
    "screenshot": "",
    "links": {
      "repo": "https://github.com/SirWhack/LifeStrands",
      "demo": "",
      "writeup": ""
    }
  },
  {
    "idx": 4,
    "slug": "l-o-o-t",
    "title": "L.O.O.T.",
    "blurb": "",
    "longBlurb": "",
    "writeup": "",
    "tags": [],
    "meta": "updated sep 2025",
    "stack": "",
    "status": "active",
    "featured": false,
    "screenshot": "",
    "links": {
      "repo": "https://github.com/SirWhack/L.O.O.T.",
      "demo": "",
      "writeup": ""
    }
  }
]
